bukmacherska/__init__.py
bukmacherska/bukmacherska.py
bukmacherska_lib-1.5.0.dist-info/METADATA
bukmacherska_lib-1.5.0.dist-info/WHEEL
bukmacherska_lib-1.5.0.dist-info/top_level.txt
bukmacherska_lib-1.5.0.dist-info/RECORD
